xicam/gui/__init__.py
xicam/gui/_version.py
xicam/gui/cammart/__init__.py
xicam/gui/cammart/cammart.yapsy-plugin
xicam/gui/clientonlymodels/LocalFileSystemResource.py
xicam/gui/clientonlymodels/LocalFileSystemResource.yapsy-plugin
xicam/gui/clientonlymodels/__init__.py
xicam/gui/patches/PyQtGraph.py
xicam/gui/patches/__init__.py
xicam/gui/settings/__init__.py
xicam/gui/settings/appearance.py
xicam/gui/settings/appearance.yapsy-plugin
xicam/gui/settings/venvs.py
xicam/gui/settings/venvs.yapsy-plugin
xicam/gui/static/__init__.py
xicam/gui/static/icons/3dpreview.png
xicam/gui/static/icons/G.png
xicam/gui/static/icons/Iq2.png
xicam/gui/static/icons/Iq3.png
xicam/gui/static/icons/Iq4.png
xicam/gui/static/icons/P.png
xicam/gui/static/icons/__init__.py
xicam/gui/static/icons/addfunction.png
xicam/gui/static/icons/blackwhite.png
xicam/gui/static/icons/box.png
xicam/gui/static/icons/cake.png
xicam/gui/static/icons/calibrate.png
xicam/gui/static/icons/chi.png
xicam/gui/static/icons/clear.png
xicam/gui/static/icons/colors.png
xicam/gui/static/icons/configure.png
xicam/gui/static/icons/disable.png
xicam/gui/static/icons/down.png
xicam/gui/static/icons/ellipsis.png
xicam/gui/static/icons/enable.png
xicam/gui/static/icons/filter.png
xicam/gui/static/icons/folder.png
xicam/gui/static/icons/gofr.png
xicam/gui/static/icons/gofrvec.png
xicam/gui/static/icons/minus.png
xicam/gui/static/icons/multiplot.png
xicam/gui/static/icons/multislice.png
xicam/gui/static/icons/open.png
xicam/gui/static/icons/pause.png
xicam/gui/static/icons/plus.png
xicam/gui/static/icons/python.png
xicam/gui/static/icons/q.png
xicam/gui/static/icons/raw.png
xicam/gui/static/icons/refresh.png
xicam/gui/static/icons/remesh.png
xicam/gui/static/icons/run.png
xicam/gui/static/icons/save.png
xicam/gui/static/icons/search.png
xicam/gui/static/icons/slice.png
xicam/gui/static/icons/stop.png
xicam/gui/static/icons/trash.png
xicam/gui/static/icons/up.png
xicam.gui-2.1.5.dist-info/METADATA
xicam.gui-2.1.5.dist-info/RECORD
xicam.gui-2.1.5.dist-info/WHEEL
xicam.gui-2.1.5.dist-info/top_level.txt
